{
  "id": "java-cas-mechanism-aba",
  "subject": "Java CAS操作机制与ABA问题",
  "category": "并发",
  "difficulty": "中等",
  "tags": [
    "并发",
    "CAS",
    "原子操作"
  ],
  "content": {
    "principles": "CAS（Compare-And-Swap）是一种CPU级别的原子操作指令（如x86的cmpxchg），用于实现无锁并发。它包含三个操作数：内存位置V、预期原值A和新值B。仅当V中的值等于A时，才将V的值更新为B，否则不执行任何操作。整个过程是原子的。Java通过sun.misc.Unsafe类提供底层CAS支持，AtomicInteger等原子类（如incrementAndGet()）即基于此实现自旋更新。CAS避免了锁的阻塞，适用于低竞争场景。但其存在ABA问题：即值从A变为B又变回A，CAS会误认为未变化。解决方案是使用带版本号的AtomicStampedReference。此外，CAS在高竞争下自旋开销大，且只能保证单一变量的原子性。",
    "pitfalls": [
      "认为CAS完全无开销，忽略了在高竞争下持续自旋的CPU消耗。",
      "忽略ABA问题，在存在中间状态有业务影响的场景（如链表头指针）下直接使用CAS会导致逻辑错误。",
      "试图用CAS保证多个变量的原子性，这是做不到的，需要借助锁或合并变量。"
    ],
    "follow_up_paths": [
      "AtomicStampedReference是如何解决ABA问题的？（内部维护一个对象引用和一个整型版本号，CAS同时比较引用和版本号）",
      "Java中除了AtomicInteger，还有哪些基于CAS的高级数据结构？（如LongAdder, ConcurrentLinkedQueue）"
    ]
  }
}
