{
  "id": "short-url-system-design",
  "subject": "短链系统设计核心",
  "category": "系统设计",
  "difficulty": "中等",
  "tags": [
    "系统设计",
    "短链",
    "缓存"
  ],
  "content": {
    "principles": "短链系统本质是将长 URL 映射到短字符串，核心挑战是生成唯一短码并能反向查找。\n\n1. **短码生成策略**：\n   - 避免使用数据库自增 ID 直接转 62 进制（易被遍历猜测）。\n   - 推荐使用分布式唯一 ID 生成器（如 Snowflake 算法）生成 64 位 long 型 ID，再转换为 62 进制（a-z, A-Z, 0-9）字符串，长度通常为 6-8 位。\n2. **存储与缓存**：\n   - 存储结构为 KV，短码作主键，存储原始 URL 和过期时间。\n   - 读多写少，使用 Redis 作为缓存扛压。先查缓存，未命中再查 MySQL/TiDB。\n   - 写操作需保证缓存与数据库双写一致性，通常采用删除缓存而非更新缓存策略。\n3. **跳转接口**：使用 HTTP 302 重定向，响应头 `Location` 填原始 URL。注意短码大小写敏感问题，建议统一转为小写处理。\n4. **防刷与限流**：使用 Redis 记录 IP 访问频次，结合滑动窗口算法进行限流，防止爬虫。\n5. **扩展功能（如点击统计）**：避免直接更新主表导致行锁。可将点击事件异步发送至 Kafka，由下游消费并写入 HBase 或 ClickHouse 进行分析。",
    "pitfalls": [
      "使用简单哈希（如 MD5）生成短码，忽略碰撞和安全性问题。",
      "缓存策略不当，导致缓存穿透、击穿或雪崩。",
      "忽略短码的唯一性冲突处理（如重试机制）。"
    ],
    "follow_up_paths": [
      "如何设计一个高可用的分布式 ID 生成器来支撑短码生成？",
      "当缓存集群故障时，如何保证系统降级后仍能提供服务？",
      "如何设计一个支持自定义短码（个性化短链）的系统？"
    ]
  }
}
