{
  "id": "java-volatile-happens-before",
  "subject": "Java volatile 与 happens-before 规则",
  "category": "hot200",
  "difficulty": "中等",
  "tags": [
    "Java",
    "并发",
    "内存模型"
  ],
  "content": {
    "principles": "happens-before 规则定义了 Java 内存模型中操作之间的偏序关系，是判断数据竞争和内存可见性的依据。volatile 变量的写操作与后续对该变量的读操作之间存在 happens-before 关系，这保证了写操作的结果对后续读操作是可见的。在双重检查锁定单例模式中，如果 instance 变量不加 volatile，由于指令重排序，可能导致其他线程看到一个尚未完全初始化的对象（即对象引用已赋值，但构造函数未执行完毕）。volatile 通过内存屏障禁止了这种特定类型的重排序，从而保证了安全性。synchronized 块也能保证可见性和有序性，但 volatile 是一种更轻量级的解决方案。",
    "pitfalls": [
      "认为 volatile 能保证复合操作（如 i++）的原子性。",
      "不理解为什么双重检查锁定中必须使用 volatile，认为 synchronized 已经足够。",
      "混淆 happens-before 与程序执行顺序，不理解它是保证可见性的规则，而非执行顺序的强制约束。"
    ],
    "follow_up_paths": [
      "volatile 底层是如何通过内存屏障实现的？在 x86 和 ARM 架构上有什么不同？",
      "除了 volatile，还有哪些操作或关键字能建立 happens-before 关系？（如 synchronized 的解锁/加锁、Thread.start()、Thread.join() 等）",
      "请解释 JMM（Java Memory Model）中关于 final 字段的特殊规则。"
    ]
  }
}